copulogram/Copulogram.py
copulogram/NonParametricModel.py
copulogram/__init__.py
copulogram/deprecated_Copulogram.py
copulogram-0.0.4.dist-info/LICENSE
copulogram-0.0.4.dist-info/METADATA
copulogram-0.0.4.dist-info/WHEEL
copulogram-0.0.4.dist-info/top_level.txt
copulogram-0.0.4.dist-info/RECORD
