Metadata-Version: 2.1
Name: copulogram
Version: 0.0.4
Summary: Data visualization for multivariate datasets with a nonlinear dependence structure
Home-page: https://github.com/efekhari27/copulogram
Author: Elias Fekhari, Vincent Chabridon
Author-email: elias.fekhari@edf.fr
License: LGPLv3+
Keywords: OpenTURNS,Copula
Classifier: Environment :: Console
Classifier: Intended Audience :: Science/Research
Classifier: Intended Audience :: Developers
Classifier: Natural Language :: English
Classifier: Programming Language :: Python :: 3
Classifier: Topic :: Software Development
Classifier: Topic :: Scientific/Engineering
License-File: LICENSE
Requires-Dist: pandas
Requires-Dist: seaborn
Requires-Dist: matplotlib
Requires-Dist: openturns (>=1.20)
